LNMarketBot/BacktestBroker.py
LNMarketBot/BinanceData.py
LNMarketBot/BitfinexBroker.py
LNMarketBot/BitfinexData.py
LNMarketBot/Bot.py
LNMarketBot/Broker.py
LNMarketBot/CSVData.py
LNMarketBot/Data.py
LNMarketBot/KrakenData.py
LNMarketBot/LNMBroker.py
LNMarketBot/LNMData.py
LNMarketBot/Notifier.py
LNMarketBot/Order.py
LNMarketBot/Strategy.py
LNMarketBot/__init__.py
LNMarketBot-0.3.6.dist-info/LICENSE
LNMarketBot-0.3.6.dist-info/METADATA
LNMarketBot-0.3.6.dist-info/WHEEL
LNMarketBot-0.3.6.dist-info/top_level.txt
LNMarketBot-0.3.6.dist-info/RECORD
