Metadata-Version: 2.1
Name: LNMarketBot
Version: 0.3.6
Summary: Trading Bot for LNMarkets
Home-page: https://github.com/DivyanshuBagga/LNMarketBot
Author: Divyanshu Bagga
Author-email: divyanshu.baggar@pm.me
License: MIT
Download-URL: https://github.com/DivyanshuBagga/LNMarketBot/archive/0.3.6.tar.gz
Keywords: Bitcoin,Finance,Trading
Platform: UNKNOWN
Requires-Python: >=3.6
Requires-Dist: requests
Requires-Dist: krakenex
Requires-Dist: pykrakenapi
Requires-Dist: LNMarkets
Requires-Dist: notifiers
Requires-Dist: nest-asyncio
